reco_eval_tool/__init__.py
reco_eval_tool/analysis.py
reco_eval_tool/path.py
reco_eval_tool/datasets/__init__.py
reco_eval_tool/datasets/_base.py
reco_eval_tool/metrics/__init__.py
reco_eval_tool/metrics/_base.py
reco_eval_tool/metrics/_ranking.py
reco_eval_tool/sample/__init__.py
reco_eval_tool/sample/_base.py
reco_eval_tool/statistics/__init__.py
reco_eval_tool/statistics/_base.py
reco_eval_tool/utils/__init__.py
reco_eval_tool/utils/_base.py
reco_eval_tool/visualization/__init__.py
reco_eval_tool/visualization/_base.py
tests/__init__.py
tests/datasets/__init__.py
tests/datasets/test_datasets.py
reco_eval_tool-1.1.5.dist-info/METADATA
reco_eval_tool-1.1.5.dist-info/WHEEL
reco_eval_tool-1.1.5.dist-info/top_level.txt
reco_eval_tool-1.1.5.dist-info/RECORD
