Metadata-Version: 2.1
Name: reco_eval_tool
Version: 1.1.5
Summary: Reco evaluation tool
Author: Minglei Guo
Author-email: <mingleiguo@microsoft.com>
Keywords: evaluation,precision,recall,F1
Classifier: Development Status :: 3 - Alpha
Classifier: Intended Audience :: Education
Classifier: Programming Language :: Python :: 3
Classifier: Operating System :: MacOS :: MacOS X
Classifier: Operating System :: Microsoft :: Windows
Requires-Dist: pandas
Requires-Dist: numpy
Requires-Dist: seaborn
Requires-Dist: matplotlib
Requires-Dist: scikit-learn
